MANIFEST.in
README.md
README.txt
requirements.txt
setup.py
wsgiprof/__init__.py
wsgiprof/profiler.py
wsgiprof.egg-info/PKG-INFO
wsgiprof.egg-info/SOURCES.txt
wsgiprof.egg-info/dependency_links.txt
wsgiprof.egg-info/requires.txt
wsgiprof.egg-info/top_level.txt