Metadata-Version: 1.1
Name: wsgiprof
Version: 1.0.1
Summary: Lightweight WSGI Profiler with Call Graph Visualization
Home-page: https://github.com/nya3jp/wsgiprof/
Author: Shuhei Takahashi
Author-email: takahashi.shuhei@gmail.com
License: UNKNOWN
Platform: UNKNOWN
Classifier: Development Status :: 4 - Beta
Classifier: Operating System :: OS Independent
Classifier: Programming Language :: Python :: 2.7
Classifier: Programming Language :: Python :: 3.5
Classifier: License :: OSI Approved :: Apache Software License
Classifier: Topic :: Software Development :: Libraries :: Python Modules
